<virtual-user errorPolicy="DO_NOTHING"
    failedAssertionPolicy="DO_NOTHING" slaProfileEnabled="false"
    type="LEGACY" uid="KonaKart-Angular">
    <init-container element-number="1" execution-type="0" pacingEnd="0"
        pacingMode="MODE_NO_PACING" pacingStart="0" pacingValue="0"
        slaProfileEnabled="false" weightsEnabled="false">
        <description>Elements executed once when the Virtual User starts.</description>
    </init-container>
    <actions-container clearUserIterationDataMode="AUTO"
        element-number="1" execution-type="0" pacingEnd="0"
        pacingMode="MODE_NO_PACING" pacingStart="0" pacingValue="0"
        slaProfileEnabled="false" weightsEnabled="false">
        <description>Elements repeated until the Virtual User stops.</description>
        <weighted-embedded-action uid="e99f813e-292a-4952-a9f7-22b6f84c24ac"/>
        <weighted-embedded-action uid="1fd3dc5a-2436-4167-9e53-3f1828d0158a"/>
    </actions-container>
    <end-container element-number="1" execution-type="0" pacingEnd="0"
        pacingMode="MODE_NO_PACING" pacingStart="0" pacingValue="0"
        slaProfileEnabled="false" weightsEnabled="false">
        <description>Elements executed before the Virtual User stops.</description>
        <weighted-embedded-action uid="78e3d739-97ba-462b-9f75-58a1242f6320"/>
    </end-container>
    <thinktime-policy thinkTimeMode="MODE_SIMPLE_THINK_TIME"
        thinktimeFactorValue="100" thinktimePolicy="1"
        thinktimeRangeValue="0" thinktimeValue="5000"/>
</virtual-user>
